{"q_0203":{"type":"judgement","stem":"在文本数据处理中，分词并不是所有语言的必要步骤。例如，对于某些非基于字母的语言（如中文），分词是必要的，但对于一些基于字母的语言（如英文），单词之间通常有空格分隔，因此分词不是必需的。","options":[],"answer":"√","explanation":"中文等语言需要切词处理，而英文因空格天然分词清晰，可直接处理。","dedupe_key":"bd70614c553431bf","raw_id":"raw_0203","sources":[{"source":"AI训练师理论知识详解三级_高级.pdf","source_question_number":"203","source_section":"判断题","source_page":null}],"id":"q_0203","category":"智能系统设计","category_confidence":0.95,"classification_reason":"AI训练师理论知识详解三级_高级.pdf 第 203 题落在 196-285 题号段","classification_method":"source_question_range","knowledge_point":"文本处理与分词","knowledge_reason":"关键词：文本数据、分词"},"q_0503":{"type":"single","stem":"在文本数据拆解过程中，分词的主要目的是( )。","options":["A. 将文本切分成单词或短语 (B) 识别文本中的命名实体","C. 判断文本的情感倾向 (D) 分析文本的语法结构"],"answer":"A","explanation":"将文本切分为最小有意义单位，便于分析。","dedupe_key":"389110fbddcda5f9","raw_id":"raw_0503","sources":[{"source":"AI训练师理论知识详解三级_高级.pdf","source_question_number":"203","source_section":"单选题","source_page":null},{"source":"第3部分-理论知识复习题.docx","source_question_number":"203","source_section":"单选题","source_page":null}],"id":"q_0503","category":"智能系统设计","category_confidence":0.95,"classification_reason":"AI训练师理论知识详解三级_高级.pdf 第 203 题落在 196-285 题号段","classification_method":"source_question_range","knowledge_point":"文本处理与分词","knowledge_reason":"关键词：文本数据、分词"},"q_0803":{"type":"multiple","stem":"文本数据的拆解技术主要包括（ ）方面。","options":["A. 词性标注 (B) 命名实体识别 (C) 依存关系分析","D. 语义角色标注 (E) 句法分析"],"answer":"ABCDE","explanation":"所有选项均为自然语言处理中的基本文本分析技术。","dedupe_key":"bb7517a8276edc82","raw_id":"raw_0803","sources":[{"source":"AI训练师理论知识详解三级_高级.pdf","source_question_number":"203","source_section":"多选题","source_page":null},{"source":"第3部分-理论知识复习题.docx","source_question_number":"203","source_section":"多选题","source_page":null}],"id":"q_0803","category":"智能系统设计","category_confidence":0.95,"classification_reason":"AI训练师理论知识详解三级_高级.pdf 第 203 题落在 196-285 题号段","classification_method":"source_question_range","knowledge_point":"文本处理与分词","knowledge_reason":"关键词：文本数据、自然语言"},"q_0210":{"type":"judgement","stem":"在自然语言处理中，特征工程不仅用于文本数据的降维处理，还涉及许多其他方面，如词嵌入、词性标注等。","options":[],"answer":"√","explanation":"表述完整，特征工程在 NLP 中涵盖多个层次。","dedupe_key":"cce675c0f7923036","raw_id":"raw_0210","sources":[{"source":"AI训练师理论知识详解三级_高级.pdf","source_question_number":"210","source_section":"判断题","source_page":null}],"id":"q_0210","category":"智能系统设计","category_confidence":0.95,"classification_reason":"AI训练师理论知识详解三级_高级.pdf 第 210 题落在 196-285 题号段","classification_method":"source_question_range","knowledge_point":"文本处理与分词","knowledge_reason":"关键词：文本数据、自然语言"},"q_0510":{"type":"single","stem":"在自然语言处理中，( )方法可以用于文本预处理。","options":["A. 使用神经网络进行文本分类 (B) 对文本进行情感分析","C. 对文本进行分词和去停用词 (D) 使用TF-IDF进行特征选择"],"answer":"C","explanation":"分词与去停用词是基本预处理操作。","dedupe_key":"fad8a7bfe73df5fb","raw_id":"raw_0510","sources":[{"source":"AI训练师理论知识详解三级_高级.pdf","source_question_number":"210","source_section":"单选题","source_page":null},{"source":"第3部分-理论知识复习题.docx","source_question_number":"210","source_section":"单选题","source_page":null},{"source":"第5部分-理论知识模拟试卷.docx","source_question_number":"134","source_section":"单选题","source_page":null}],"id":"q_0510","category":"智能系统设计","category_confidence":0.95,"classification_reason":"AI训练师理论知识详解三级_高级.pdf 第 210 题落在 196-285 题号段","classification_method":"source_question_range","knowledge_point":"文本处理与分词","knowledge_reason":"关键词：分词、停用词、TF-IDF、自然语言"},"q_0810":{"type":"multiple","stem":"机器学习特征工程在自然语言处理中的应用主要包括（ ）。","options":["A. 文本分类 (B) 情感分析 (C) 命名实体识别","D. 推荐系统 (E) 拼写检查和语法纠错"],"answer":"ABC","explanation":"文本分类、情感分析、实体识别都是 NLP 中的特征工程实践。","dedupe_key":"50e3e9e6bcae4c43","raw_id":"raw_0810","sources":[{"source":"AI训练师理论知识详解三级_高级.pdf","source_question_number":"210","source_section":"多选题","source_page":null},{"source":"第3部分-理论知识复习题.docx","source_question_number":"210","source_section":"多选题","source_page":null}],"id":"q_0810","category":"智能系统设计","category_confidence":0.95,"classification_reason":"AI训练师理论知识详解三级_高级.pdf 第 210 题落在 196-285 题号段","classification_method":"source_question_range","knowledge_point":"文本处理与分词","knowledge_reason":"关键词：自然语言"},"q_0266":{"type":"judgement","stem":"人工智能在人机交互中主要应用于提高系统的安全性。","options":[],"answer":"×","explanation":"AI更多用于自然语言处理、推荐系统、智能助手等。","dedupe_key":"e93225968a61d9d3","raw_id":"raw_0266","sources":[{"source":"AI训练师理论知识详解三级_高级.pdf","source_question_number":"266","source_section":"判断题","source_page":null},{"source":"第3部分-理论知识复习题.docx","source_question_number":"266","source_section":"判断题","source_page":null}],"id":"q_0266","category":"智能系统设计","category_confidence":0.95,"classification_reason":"AI训练师理论知识详解三级_高级.pdf 第 266 题落在 196-285 题号段","classification_method":"source_question_range","knowledge_point":"文本处理与分词","knowledge_reason":"关键词：自然语言"},"q_0814":{"type":"multiple","stem":"在文本数据预处理中，常见的步骤包括（ ）。","options":["A. 分词 (B) 去除停用词 (C) 词干提取和词形还原","D. 将文本转换为数字向量表示 (E) 增加文本的字数"],"answer":"ABCD","explanation":"分词、去停用词、词干/还原、向量化是文本处理基础；增加字数无效。","dedupe_key":"5375bf2e7f65221a","raw_id":"raw_0814","sources":[{"source":"AI训练师理论知识详解三级_高级.pdf","source_question_number":"214","source_section":"多选题","source_page":null},{"source":"第3部分-理论知识复习题.docx","source_question_number":"214","source_section":"多选题","source_page":null}],"id":"q_0814","category":"智能系统设计","category_confidence":0.95,"classification_reason":"AI训练师理论知识详解三级_高级.pdf 第 214 题落在 196-285 题号段","classification_method":"source_question_range","knowledge_point":"文本处理与分词","knowledge_reason":"关键词：文本数据、分词、停用词"},"q_0926":{"type":"judgement","stem":"在文本数据处理中，分词是所有语言的必要步骤。","options":[],"answer":"×","explanation":"分词并不是所有语言都必须的步骤，不同语言和文本处理任务对分词的需求不同。","dedupe_key":"c52cfeed41d5fd9b","raw_id":"raw_1103","sources":[{"source":"第3部分-理论知识复习题.docx","source_question_number":"203","source_section":"判断题","source_page":null}],"id":"q_0926","category":"智能系统设计","category_confidence":0.95,"classification_reason":"第3部分-理论知识复习题.docx 第 203 题落在 196-285 题号段","classification_method":"source_question_range","answer_source":"answer_overrides","knowledge_point":"文本处理与分词","knowledge_reason":"关键词：文本数据、分词"},"q_0827":{"type":"multiple","stem":"自然语言处理中的文本分析技术主要包括（ ）方面。","options":["A. 词法分析 (B) 句法分析 (C) 语义分析","D. 情感分析 (E) 主题建模"],"answer":"ABCDE","explanation":"包括从词法到主题建模的整个 NLP 处理流程。","dedupe_key":"191829dc7ec0d0ba","raw_id":"raw_0827","sources":[{"source":"AI训练师理论知识详解三级_高级.pdf","source_question_number":"227","source_section":"多选题","source_page":null},{"source":"第3部分-理论知识复习题.docx","source_question_number":"227","source_section":"多选题","source_page":null}],"id":"q_0827","category":"智能系统设计","category_confidence":0.95,"classification_reason":"AI训练师理论知识详解三级_高级.pdf 第 227 题落在 196-285 题号段","classification_method":"source_question_range","knowledge_point":"文本处理与分词","knowledge_reason":"关键词：自然语言"},"q_0931":{"type":"judgement","stem":"在自然语言处理中，特征工程主要用于文本数据的降维处理。","options":[],"answer":"×","explanation":"自然语言处理中的特征工程包括特征提取、表示、选择和转换，不主要等同于文本降维。","dedupe_key":"315ead776a50b4b9","raw_id":"raw_1110","sources":[{"source":"第3部分-理论知识复习题.docx","source_question_number":"210","source_section":"判断题","source_page":null}],"id":"q_0931","category":"智能系统设计","category_confidence":0.95,"classification_reason":"第3部分-理论知识复习题.docx 第 210 题落在 196-285 题号段","classification_method":"source_question_range","answer_source":"answer_overrides","knowledge_point":"文本处理与分词","knowledge_reason":"关键词：文本数据、自然语言"},"q_0865":{"type":"multiple","stem":"通过（ ），使 AI 系统更好地理解用户。","options":["A. 开发高级的自然语言处理技术 (B) 集成面部表情识别技术","C. 应用情感语义分析 (D) 增加系统响应的延迟时间","E. 设计固定不变的交互模式"],"answer":"ABC","explanation":"NLP、情绪分析、表情识别都是理解用户的关键技术。","dedupe_key":"7bc5ce2fe4075d42","raw_id":"raw_0865","sources":[{"source":"AI训练师理论知识详解三级_高级.pdf","source_question_number":"265","source_section":"多选题","source_page":null},{"source":"第3部分-理论知识复习题.docx","source_question_number":"265","source_section":"多选题","source_page":null}],"id":"q_0865","category":"智能系统设计","category_confidence":0.95,"classification_reason":"AI训练师理论知识详解三级_高级.pdf 第 265 题落在 196-285 题号段","classification_method":"source_question_range","knowledge_point":"文本处理与分词","knowledge_reason":"关键词：自然语言"},"q_0204":{"type":"judgement","stem":"时间序列分析是一种预测方法，它可以通过分析历史数据来预测未来的天气情况。","options":[],"answer":"√","explanation":"时间序列广泛用于天气、金融等领域的趋势预测。","dedupe_key":"6bf24bcd5022ec31","raw_id":"raw_0204","sources":[{"source":"AI训练师理论知识详解三级_高级.pdf","source_question_number":"204","source_section":"判断题","source_page":null}],"id":"q_0204","category":"智能系统设计","category_confidence":0.95,"classification_reason":"AI训练师理论知识详解三级_高级.pdf 第 204 题落在 196-285 题号段","classification_method":"source_question_range","knowledge_point":"时间序列与预测分析","knowledge_reason":"关键词：时间序列、预测未来"},"q_0502":{"type":"single","stem":"对于非平稳时间序列数据，通过减去先前观察值来消除趋势和季节性的过程叫做( )。","options":["A. 对数变换 (B) 标准化","C. 差分 (D) 归一化"],"answer":"C","explanation":"差分是常用的平稳化处理手段。","dedupe_key":"d175f99e581ebe2d","raw_id":"raw_0502","sources":[{"source":"AI训练师理论知识详解三级_高级.pdf","source_question_number":"202","source_section":"单选题","source_page":null},{"source":"第3部分-理论知识复习题.docx","source_question_number":"202","source_section":"单选题","source_page":null}],"id":"q_0502","category":"智能系统设计","category_confidence":0.95,"classification_reason":"AI训练师理论知识详解三级_高级.pdf 第 202 题落在 196-285 题号段","classification_method":"source_question_range","knowledge_point":"时间序列与预测分析","knowledge_reason":"关键词：时间序列"},"q_0802":{"type":"multiple","stem":"在进行时间序列数据的拆解和处理时，通常需要考虑（ ）因素。","options":["A. 数据的周期性 (B) 数据的趋势性 (C) 数据的季节性","D. 数据的随机性 (E) 数据的分组特征"],"answer":"ABCD","explanation":"时间序列分析需识别周期性、趋势性、季节性和随机性。","dedupe_key":"c0ac1d9eb6b0c6f2","raw_id":"raw_0802","sources":[{"source":"AI训练师理论知识详解三级_高级.pdf","source_question_number":"202","source_section":"多选题","source_page":null},{"source":"第3部分-理论知识复习题.docx","source_question_number":"202","source_section":"多选题","source_page":null}],"id":"q_0802","category":"智能系统设计","category_confidence":0.95,"classification_reason":"AI训练师理论知识详解三级_高级.pdf 第 202 题落在 196-285 题号段","classification_method":"source_question_range","knowledge_point":"时间序列与预测分析","knowledge_reason":"关键词：时间序列"},"q_0207":{"type":"judgement","stem":"多维度数据分解的原理不仅适用于数值型数据，也适用于其他类型的数据，如文本、图像等。","options":[],"answer":"√","explanation":"表述正确，多维数据分解方法如张量分解可扩展至多种数据类型。","dedupe_key":"bfdd2bc193b07ee6","raw_id":"raw_0207","sources":[{"source":"AI训练师理论知识详解三级_高级.pdf","source_question_number":"207","source_section":"判断题","source_page":null}],"id":"q_0207","category":"智能系统设计","category_confidence":0.95,"classification_reason":"AI训练师理论知识详解三级_高级.pdf 第 207 题落在 196-285 题号段","classification_method":"source_question_range","knowledge_point":"时间序列与预测分析","knowledge_reason":"题号 207 落在 206-215 的知识点段"},"q_0504":{"type":"single","stem":"时间序列分析在天气预报中主要用于( )目的。","options":["A. 预测未来天气变化 (B) 分析历史气温趋势","C. 改善气象站设备 (D) 教育公众关于气候变化"],"answer":"A","explanation":"通过历史数据预测未来趋势是其关键应用。","dedupe_key":"14245fc4539b5896","raw_id":"raw_0504","sources":[{"source":"AI训练师理论知识详解三级_高级.pdf","source_question_number":"204","source_section":"单选题","source_page":null},{"source":"第3部分-理论知识复习题.docx","source_question_number":"204","source_section":"单选题","source_page":null}],"id":"q_0504","category":"智能系统设计","category_confidence":0.95,"classification_reason":"AI训练师理论知识详解三级_高级.pdf 第 204 题落在 196-285 题号段","classification_method":"source_question_range","knowledge_point":"时间序列与预测分析","knowledge_reason":"关键词：时间序列、预测未来"},"q_0804":{"type":"multiple","stem":"时间序列分析在天气预报中的主要作用是（ ）。","options":["A. 预测未来天气状况 (B) 分析历史天气数据 (C) 确定天气变化趋势","D. 评估天气模型的准确性 (E) 优化气象观测网络"],"answer":"ABCD","explanation":"可用于预测、分析历史、识别趋势和评估模型性能。","dedupe_key":"29a0f2e7f2996e0e","raw_id":"raw_0804","sources":[{"source":"AI训练师理论知识详解三级_高级.pdf","source_question_number":"204","source_section":"多选题","source_page":null},{"source":"第3部分-理论知识复习题.docx","source_question_number":"204","source_section":"多选题","source_page":null}],"id":"q_0804","category":"智能系统设计","category_confidence":0.95,"classification_reason":"AI训练师理论知识详解三级_高级.pdf 第 204 题落在 196-285 题号段","classification_method":"source_question_range","knowledge_point":"时间序列与预测分析","knowledge_reason":"关键词：时间序列、预测未来"},"q_0209":{"type":"judgement","stem":"特征提取是指从原始数据中提取出对模型预测有帮助的特征。","options":[],"answer":"√","explanation":"这是特征工程的重要一环，对模型性能有显著影响。","dedupe_key":"c218a12e618b8745","raw_id":"raw_0209","sources":[{"source":"AI训练师理论知识详解三级_高级.pdf","source_question_number":"209","source_section":"判断题","source_page":null},{"source":"第3部分-理论知识复习题.docx","source_question_number":"209","source_section":"判断题","source_page":null}],"id":"q_0209","category":"智能系统设计","category_confidence":0.95,"classification_reason":"AI训练师理论知识详解三级_高级.pdf 第 209 题落在 196-285 题号段","classification_method":"source_question_range","knowledge_point":"时间序列与预测分析","knowledge_reason":"题号 209 落在 206-215 的知识点段"},"q_0515":{"type":"single","stem":"在数据分析的标准流程中，( )步骤是紧接着收集数据之后进行的。","options":["A. 数据清洗 (B) 数据可视化","C. 数据挖掘 (D) 数据分析"],"answer":"A","explanation":"清洗确保数据质量，为分析做好准备。","dedupe_key":"848284db2cf55872","raw_id":"raw_0515","sources":[{"source":"AI训练师理论知识详解三级_高级.pdf","source_question_number":"215","source_section":"单选题","source_page":null},{"source":"第3部分-理论知识复习题.docx","source_question_number":"215","source_section":"单选题","source_page":null},{"source":"第5部分-理论知识模拟试卷.docx","source_question_number":"131","source_section":"单选题","source_page":null}],"id":"q_0515","category":"智能系统设计","category_confidence":0.95,"classification_reason":"AI训练师理论知识详解三级_高级.pdf 第 215 题落在 196-285 题号段","classification_method":"source_question_range","knowledge_point":"时间序列与预测分析","knowledge_reason":"题号 215 落在 206-215 的知识点段"},"q_0812":{"type":"multiple","stem":"在进行安全性分析时，需要考虑的因素包括（ ）。","options":["A. 人员因素 (B) 环境因素 (C) 技术因素","D. 管理因素 (E) 经济因素"],"answer":"ABCD","explanation":"安全性受人员、技术、环境、管理等多因素影响。","dedupe_key":"c9046c58a4166d43","raw_id":"raw_0812","sources":[{"source":"AI训练师理论知识详解三级_高级.pdf","source_question_number":"212","source_section":"多选题","source_page":null},{"source":"第3部分-理论知识复习题.docx","source_question_number":"212","source_section":"多选题","source_page":null}],"id":"q_0812","category":"智能系统设计","category_confidence":0.95,"classification_reason":"AI训练师理论知识详解三级_高级.pdf 第 212 题落在 196-285 题号段","classification_method":"source_question_range","knowledge_point":"时间序列与预测分析","knowledge_reason":"题号 212 落在 206-215 的知识点段"},"q_0215":{"type":"judgement","stem":"在数据分析过程中，数据清洗的主要目的是去除重复数据、处理缺失值和异常值等，以提高数据质量。","options":[],"answer":"√","explanation":"数据清洗是整个分析流程的第一步，决定后续建模效果。","dedupe_key":"f51f21ac60864a23","raw_id":"raw_0215","sources":[{"source":"AI训练师理论知识详解三级_高级.pdf","source_question_number":"215","source_section":"判断题","source_page":null}],"id":"q_0215","category":"智能系统设计","category_confidence":0.95,"classification_reason":"AI训练师理论知识详解三级_高级.pdf 第 215 题落在 196-285 题号段","classification_method":"source_question_range","knowledge_point":"时间序列与预测分析","knowledge_reason":"题号 215 落在 206-215 的知识点段"},"q_0525":{"type":"single","stem":"循环神经网络 RNN 的核心思想是( )。","options":["A. 通过反向传播算法优化网络参数 (B) 利用门控机制处理序列数据","C. 使用注意力机制捕捉长距离依赖关系 (D) 采用自编码器进行特征提取"],"answer":"B","explanation":"门控机制处理时间序列中的长依赖问题。","dedupe_key":"fed0cd7d6a3a31fc","raw_id":"raw_0525","sources":[{"source":"AI训练师理论知识详解三级_高级.pdf","source_question_number":"225","source_section":"单选题","source_page":null},{"source":"第3部分-理论知识复习题.docx","source_question_number":"225","source_section":"单选题","source_page":null},{"source":"第5部分-理论知识模拟试卷.docx","source_question_number":"111","source_section":"单选题","source_page":null}],"id":"q_0525","category":"智能系统设计","category_confidence":0.95,"classification_reason":"AI训练师理论知识详解三级_高级.pdf 第 225 题落在 196-285 题号段","classification_method":"source_question_range","knowledge_point":"时间序列与预测分析","knowledge_reason":"关键词：时间序列"},"q_0815":{"type":"multiple","stem":"数据分析的标准流程通常包括（ ）步骤。","options":["A. 数据收集 (B) 数据清洗 (C) 数据可视化","D. 数据挖掘 (E) 数据分析报告"],"answer":"ABCDE","explanation":"从收集到报告，数据分析需经历完整链条。","dedupe_key":"b85953921e316e74","raw_id":"raw_0815","sources":[{"source":"AI训练师理论知识详解三级_高级.pdf","source_question_number":"215","source_section":"多选题","source_page":null},{"source":"第3部分-理论知识复习题.docx","source_question_number":"215","source_section":"多选题","source_page":null}],"id":"q_0815","category":"智能系统设计","category_confidence":0.95,"classification_reason":"AI训练师理论知识详解三级_高级.pdf 第 215 题落在 196-285 题号段","classification_method":"source_question_range","knowledge_point":"时间序列与预测分析","knowledge_reason":"题号 215 落在 206-215 的知识点段"},"q_0228":{"type":"judgement","stem":"时间序列分析不仅可以处理线性数据，还可以处理非线性数据。它通过分析时间序列数据中的模式和趋势来预测未来的值。","options":[],"answer":"√","explanation":"该说法准确，现代时间序列方法支持非线性建模，如 LSTM、ARIMA 扩展等。","dedupe_key":"29cf451f688de03d","raw_id":"raw_0228","sources":[{"source":"AI训练师理论知识详解三级_高级.pdf","source_question_number":"228","source_section":"判断题","source_page":null}],"id":"q_0228","category":"智能系统设计","category_confidence":0.95,"classification_reason":"AI训练师理论知识详解三级_高级.pdf 第 228 题落在 196-285 题号段","classification_method":"source_question_range","knowledge_point":"时间序列与预测分析","knowledge_reason":"关键词：时间序列、预测未来"},"q_0528":{"type":"single","stem":"时间序列分析中，( )方法用于移除趋势和季节性效应。","options":["A. 平稳性检验 (B) 季节分解","C. 自相关函数 (D) 累积和控制图"],"answer":"B","explanation":"季节分解提取趋势、季节、残差成分。","dedupe_key":"f1fd05e8ec240cfd","raw_id":"raw_0528","sources":[{"source":"AI训练师理论知识详解三级_高级.pdf","source_question_number":"228","source_section":"单选题","source_page":null},{"source":"第3部分-理论知识复习题.docx","source_question_number":"228","source_section":"单选题","source_page":null}],"id":"q_0528","category":"智能系统设计","category_confidence":0.95,"classification_reason":"AI训练师理论知识详解三级_高级.pdf 第 228 题落在 196-285 题号段","classification_method":"source_question_range","knowledge_point":"时间序列与预测分析","knowledge_reason":"关键词：时间序列"},"q_0828":{"type":"multiple","stem":"在进行时间序列分析时，（ ）步骤是必要的。","options":["A. 数据清洗 (B) 异常值检测 (C) 趋势分析","D. 周期性分析 (E) 预测未来趋势"],"answer":"ABCDE","explanation":"清洗、异常检测、趋势周期分析与未来预测是关键步骤","dedupe_key":"5eeea38de45f1298","raw_id":"raw_0828","sources":[{"source":"AI训练师理论知识详解三级_高级.pdf","source_question_number":"228","source_section":"多选题","source_page":null},{"source":"第3部分-理论知识复习题.docx","source_question_number":"228","source_section":"多选题","source_page":null}],"id":"q_0828","category":"智能系统设计","category_confidence":0.95,"classification_reason":"AI训练师理论知识详解三级_高级.pdf 第 228 题落在 196-285 题号段","classification_method":"source_question_range","knowledge_point":"时间序列与预测分析","knowledge_reason":"关键词：时间序列、预测未来"},"q_0927":{"type":"judgement","stem":"时间序列分析是一种预测方法，它可以帮助我们预测未来的天气情况。","options":[],"answer":"√","explanation":"时间序列分析可利用历史时间序列数据预测未来趋势，天气预测是典型应用之一。","dedupe_key":"cd7369bffa09b78d","raw_id":"raw_1104","sources":[{"source":"第3部分-理论知识复习题.docx","source_question_number":"204","source_section":"判断题","source_page":null}],"id":"q_0927","category":"智能系统设计","category_confidence":0.95,"classification_reason":"第3部分-理论知识复习题.docx 第 204 题落在 196-285 题号段","classification_method":"source_question_range","answer_source":"answer_overrides","knowledge_point":"时间序列与预测分析","knowledge_reason":"关键词：时间序列、预测未来、天气情况"},"q_0549":{"type":"single","stem":"在 AI产品的迭代过程中，用户反馈的主要作用是( )。","options":["A. 确定产品功能方向 (B) 评估市场营销策略","C. 优化产品性能和用户体验 (D) 预测未来市场趋势"],"answer":"C","explanation":"实际使用情况能指导性能与体验改进。","dedupe_key":"a721960c2aac7a7d","raw_id":"raw_0549","sources":[{"source":"AI训练师理论知识详解三级_高级.pdf","source_question_number":"249","source_section":"单选题","source_page":null},{"source":"第3部分-理论知识复习题.docx","source_question_number":"249","source_section":"单选题","source_page":null},{"source":"第5部分-理论知识模拟试卷.docx","source_question_number":"106","source_section":"单选题","source_page":null}],"id":"q_0549","category":"智能系统设计","category_confidence":0.95,"classification_reason":"AI训练师理论知识详解三级_高级.pdf 第 249 题落在 196-285 题号段","classification_method":"source_question_range","knowledge_point":"时间序列与预测分析","knowledge_reason":"关键词：预测未来"},"q_0929":{"type":"judgement","stem":"多维度数据分解的原理仅适用于数值型数据。","options":[],"answer":"×","explanation":"","dedupe_key":"8b2ff89d2dd4bd79","raw_id":"raw_1107","sources":[{"source":"第3部分-理论知识复习题.docx","source_question_number":"207","source_section":"判断题","source_page":null},{"source":"第5部分-理论知识模拟试卷.docx","source_question_number":"34","source_section":"判断题","source_page":null}],"id":"q_0929","category":"智能系统设计","category_confidence":0.95,"classification_reason":"第3部分-理论知识复习题.docx 第 207 题落在 196-285 题号段","classification_method":"source_question_range","knowledge_point":"时间序列与预测分析","knowledge_reason":"题号 207 落在 206-215 的知识点段"},"q_0933":{"type":"judgement","stem":"在人工智能系统的训练过程中，人工智能训练师不需要关注模型的安全性分析。","options":[],"answer":"×","explanation":"人工智能系统训练过程中需要关注模型安全性，避免漏洞、滥用、攻击和风险输出。","dedupe_key":"85c1724dd9a8d75f","raw_id":"raw_1112","sources":[{"source":"第3部分-理论知识复习题.docx","source_question_number":"212","source_section":"判断题","source_page":null}],"id":"q_0933","category":"智能系统设计","category_confidence":0.95,"classification_reason":"第3部分-理论知识复习题.docx 第 212 题落在 196-285 题号段","classification_method":"source_question_range","answer_source":"answer_overrides","knowledge_point":"时间序列与预测分析","knowledge_reason":"题号 212 落在 206-215 的知识点段"},"q_0935":{"type":"judgement","stem":"在数据分析过程中，数据清洗的主要目的是去除重复数据、处理缺失值和异常值。","options":[],"answer":"√","explanation":"数据清洗通常包括去重、缺失值处理、异常值处理和格式修正等。","dedupe_key":"60475e94af0f844f","raw_id":"raw_1115","sources":[{"source":"第3部分-理论知识复习题.docx","source_question_number":"215","source_section":"判断题","source_page":null}],"id":"q_0935","category":"智能系统设计","category_confidence":0.95,"classification_reason":"第3部分-理论知识复习题.docx 第 215 题落在 196-285 题号段","classification_method":"source_question_range","answer_source":"answer_overrides","knowledge_point":"时间序列与预测分析","knowledge_reason":"题号 215 落在 206-215 的知识点段"},"q_0948":{"type":"judgement","stem":"时间序列分析只能处理线性数据。","options":[],"answer":"×","explanation":"时间序列分析可处理线性和非线性时间序列，不能说只能处理线性数据。","dedupe_key":"4034bf8a2f3d374c","raw_id":"raw_1128","sources":[{"source":"第3部分-理论知识复习题.docx","source_question_number":"228","source_section":"判断题","source_page":null}],"id":"q_0948","category":"智能系统设计","category_confidence":0.95,"classification_reason":"第3部分-理论知识复习题.docx 第 228 题落在 196-285 题号段","classification_method":"source_question_range","answer_source":"answer_overrides","knowledge_point":"时间序列与预测分析","knowledge_reason":"关键词：时间序列"},"q_0206":{"type":"judgement","stem":"社会网络分析不仅关注个体之间的社会联系，还关注网络结构对个体行为、信息传播等的影响。","options":[],"answer":"√","explanation":"描述准确，体现了社会网络分析的多层次研究视角。","dedupe_key":"4a6c80f5d86a975e","raw_id":"raw_0206","sources":[{"source":"AI训练师理论知识详解三级_高级.pdf","source_question_number":"206","source_section":"判断题","source_page":null}],"id":"q_0206","category":"智能系统设计","category_confidence":0.95,"classification_reason":"AI训练师理论知识详解三级_高级.pdf 第 206 题落在 196-285 题号段","classification_method":"source_question_range","knowledge_point":"社会网络分析","knowledge_reason":"关键词：社会网络分析、社会联系、网络结构、信息传播"},"q_0506":{"type":"single","stem":"在社会网络分析中，中心性指标用于衡量节点在网络中的重要性。( )不是正确的中心性指标。","options":["A. 度中心性 (B) 介数中心性","C. 接近中心性 (D) 平均路径长度中心性"],"answer":"D","explanation":"平均路径长度是整体结构指标，非节点中心性。","dedupe_key":"20f569f198225357","raw_id":"raw_0506","sources":[{"source":"AI训练师理论知识详解三级_高级.pdf","source_question_number":"206","source_section":"单选题","source_page":null},{"source":"第3部分-理论知识复习题.docx","source_question_number":"206","source_section":"单选题","source_page":null},{"source":"第5部分-理论知识模拟试卷.docx","source_question_number":"104","source_section":"单选题","source_page":null}],"id":"q_0506","category":"智能系统设计","category_confidence":0.95,"classification_reason":"AI训练师理论知识详解三级_高级.pdf 第 206 题落在 196-285 题号段","classification_method":"source_question_range","knowledge_point":"社会网络分析","knowledge_reason":"关键词：社会网络分析"},"q_0806":{"type":"multiple","stem":"（ ）正确描述了人工智能训练师和网络分析方法在社会网络研究中的应用。","options":["A. 人工智能训练师通过标注和反馈数据，帮助机器学习算法优化社交网络中的用户行为预测模型。","B. 网络分析方法用于识别社交网络中的关键节点，从而理解信息传播的模式。","C. 人工智能训练师不直接参与社会网络分析，他们的主要工作集中在数据清洗和预处理阶段。","D. 社交网络中的大量数据为人工智能训练师提供了丰富的训练资源，用于改进推荐系统的精准度。","E. 网络分析方法通过计算节点的中心性指数，分析社交网络的结构和动态。"],"answer":"ABDE","explanation":"训练师参与行为建模与推荐，网络分析识别关键结构。","dedupe_key":"7b2010061b684b1a","raw_id":"raw_0806","sources":[{"source":"AI训练师理论知识详解三级_高级.pdf","source_question_number":"206","source_section":"多选题","source_page":null},{"source":"第3部分-理论知识复习题.docx","source_question_number":"206","source_section":"多选题","source_page":null}],"id":"q_0806","category":"智能系统设计","category_confidence":0.95,"classification_reason":"AI训练师理论知识详解三级_高级.pdf 第 206 题落在 196-285 题号段","classification_method":"source_question_range","knowledge_point":"社会网络分析","knowledge_reason":"关键词：社会网络分析、信息传播"},"q_0928":{"type":"judgement","stem":"社会网络分析主要关注个体之间的社会联系，而忽略了网络结构的影响。","options":[],"answer":"×","explanation":"社会网络分析不仅关注个体联系，也关注网络结构及其对行为、传播和关系的影响。","dedupe_key":"4ce717abfd0d2718","raw_id":"raw_1106","sources":[{"source":"第3部分-理论知识复习题.docx","source_question_number":"206","source_section":"判断题","source_page":null}],"id":"q_0928","category":"智能系统设计","category_confidence":0.95,"classification_reason":"第3部分-理论知识复习题.docx 第 206 题落在 196-285 题号段","classification_method":"source_question_range","answer_source":"answer_overrides","knowledge_point":"社会网络分析","knowledge_reason":"关键词：社会网络分析、社会联系、网络结构"},"q_0825":{"type":"multiple","stem":"深度学习中常用的网络结构包括（ ）。","options":["A. 卷积神经网络 (B) 循环神经网络 (C) 长短时记忆网络","D. 生成对抗网络 (E) 全连接神经网络"],"answer":"ABCDE","explanation":"卷积、循环、LSTM、GAN 和全连接网络是基本结构。","dedupe_key":"83e531bd32106a20","raw_id":"raw_0825","sources":[{"source":"AI训练师理论知识详解三级_高级.pdf","source_question_number":"225","source_section":"多选题","source_page":null},{"source":"第3部分-理论知识复习题.docx","source_question_number":"225","source_section":"多选题","source_page":null}],"id":"q_0825","category":"智能系统设计","category_confidence":0.95,"classification_reason":"AI训练师理论知识详解三级_高级.pdf 第 225 题落在 196-285 题号段","classification_method":"source_question_range","knowledge_point":"社会网络分析","knowledge_reason":"关键词：网络结构"}}